test_automation/__init__.py
test_automation/main.py
test_automation/models.py
test_automation/parser.py
test_automation/scheduler.py
test_automation/task_executor.py
test_automation/workflow_engine.py
flowscript-0.1.0.dist-info/METADATA
flowscript-0.1.0.dist-info/WHEEL
flowscript-0.1.0.dist-info/top_level.txt
flowscript-0.1.0.dist-info/RECORD
