Metadata-Version: 2.2
Name: FlowScript
Version: 0.1.0
Summary: A test automation package for workflow scheduling and execution.
Home-page: https://github.com/sridhar-mani/test-automation
Author: M.Sridhar
Author-email: mailtosridhar01@gmail.com
Classifier: Programming Language :: Python :: 3
Classifier: License :: OSI Approved :: Apache Software License
Classifier: Operating System :: OS Independent
Requires-Python: >=3.6
Dynamic: author
Dynamic: author-email
Dynamic: classifier
Dynamic: description
Dynamic: description-content-type
Dynamic: home-page
Dynamic: requires-python
Dynamic: summary
